sqldump2json.py
sqldump2json-1.0.3.dist-info/METADATA
sqldump2json-1.0.3.dist-info/WHEEL
sqldump2json-1.0.3.dist-info/entry_points.txt
sqldump2json-1.0.3.dist-info/RECORD
