Metadata-Version: 2.1
Name: sqldump2json
Version: 1.0.3
Summary: Converts SQL dump to a JSON stream
Home-page: https://github.com/s3rgeym/sqldump2json
License: Free for Personal Use Only
Author: Sergey M
Requires-Python: >=3.11,<4.0
Classifier: License :: Other/Proprietary License
Classifier: Programming Language :: Python :: 3
Classifier: Programming Language :: Python :: 3.11
Project-URL: Repository, https://github.com/s3rgeym/sqldump2json
